proposalsampler/__init__.py
proposalsampler/sampling/__init__.py
proposalsampler/sampling/slambda/__init__.py
proposalsampler/sampling/slambda/slambda_main.py
proposalsampler/sampling/slambda/slambda_single.py
proposalsampler/sampling/slambda/slambda_synch.py
proposalsampler/sampling/slambda/tests_slambda_main.py
proposalsampler/sampling/slambda/tests_slambda_single.py
proposalsampler/sampling/slambda/tests_slambda_synch.py
proposalsampler/sampling/slambda/tests_tree_editor.py
proposalsampler/sampling/slambda/tree_editor.py
proposalsampler/sampling/slambda/data/__init__.py
proposalsampler/sampling/slambda/data/stable.py
proposalsampler/sampling/slambda/data/gens/__init__.py
proposalsampler/sampling/slambda/data/gens/algebra/__init__.py
proposalsampler/sampling/slambda/data/gens/algebra/groups.py
proposalsampler/sampling/slambda/data/gens/algebra/src_gap.g
proposalsampler/sampling/vars/__init__.py
proposalsampler/sampling/vars/vars_extractor.py
proposalsampler/sampling/vars/vars_maps.py
proposalsampler-0.0.2.dist-info/LICENSE
proposalsampler-0.0.2.dist-info/METADATA
proposalsampler-0.0.2.dist-info/WHEEL
proposalsampler-0.0.2.dist-info/top_level.txt
proposalsampler-0.0.2.dist-info/RECORD
