Metadata-Version: 2.1
Name: proposalsampler
Version: 0.0.2
Summary: proposal sampler
Home-page: https://github.com/tokentranslator-group/proposalsampler
Author: tokentranslator-group
Author-email: 
License: UNKNOWN
Platform: UNKNOWN
